py_edl_editor/__init__.py
py_edl_editor/__main__.py
py_edl_editor/cdl_tools.py
py_edl_editor/edl_parser.py
py_edl_editor/edl_table.py
py_edl_editor/gui.py
py_edl_editor/gui_controller.py
py_edl_editor/tc_tools.py
py_edl_editor/test/__init__.py
py_edl_editor/test/test_tc_calculations.py
py_edl_editor/test/files/edl_with_gaps.edl
py_edl_editor/test/files/edl_with_gaps_start0.edl
py_edl_editor/test/files/edl_with_gaps_start0_plus_handles.edl
py_edl_editor/test/files/edl_without_gaps.edl
py_edl_editor-0.2.2.dist-info/entry_points.txt
py_edl_editor-0.2.2.dist-info/LICENSE
py_edl_editor-0.2.2.dist-info/WHEEL
py_edl_editor-0.2.2.dist-info/METADATA
py_edl_editor-0.2.2.dist-info/RECORD
