Metadata-Version: 2.1
Name: py_edl_editor
Version: 0.2.2
Summary: A cross-platform, PySide2-based EDL (Edit Decision List) GUI.
Home-page: https://github.com/ThomasWeckenmann/py_edl_editor
Author: Thomas Weckenmann
Author-email: tweckenmann0711@gmail.com
Requires-Python: >=3.7
Classifier: License :: OSI Approved :: MIT License
Requires-Dist: PySide2
Requires-Dist: cdl_convert
Requires-Dist: opentimelineio
Requires-Dist: timecode
Requires-Dist: edl
